watchgha/__init__.py
watchgha/bucketer.py
watchgha/data_core.py
watchgha/demo.py
watchgha/git_help.py
watchgha/http_help.py
watchgha/sample_data.py
watchgha/utils.py
watchgha/watch_runs.py
watchgha-2.7.0.dist-info/licenses/LICENSE.txt
watchgha-2.7.0.dist-info/METADATA
watchgha-2.7.0.dist-info/WHEEL
watchgha-2.7.0.dist-info/entry_points.txt
watchgha-2.7.0.dist-info/top_level.txt
watchgha-2.7.0.dist-info/RECORD
