Metadata-Version: 2.4
Name: watchgha
Version: 2.7.0
Summary: Watch GitHub action runs
Author-email: Ned Batchelder <ned@nedbatchelder.com>
License-Expression: Apache-2.0
Project-URL: Source code, https://github.com/nedbat/watchgha
Project-URL: Issue tracker, https://github.com/nedbat/watchgha/issues
Project-URL: Mastodon, https://hachyderm.io/@nedbat
Project-URL: Funding, https://github.com/sponsors/nedbat
Classifier: Development Status :: 5 - Production/Stable
Classifier: Programming Language :: Python
Classifier: Programming Language :: Python :: 3
Classifier: Programming Language :: Python :: 3.9
Classifier: Programming Language :: Python :: 3.10
Classifier: Programming Language :: Python :: 3.11
Classifier: Programming Language :: Python :: 3.12
Classifier: Programming Language :: Python :: 3.13
Classifier: Programming Language :: Python :: 3.14
Requires-Python: >=3.9
License-File: LICENSE.txt
Requires-Dist: click
Requires-Dist: dulwich
Requires-Dist: exceptiongroup
Requires-Dist: httpx>=0.24.1
Requires-Dist: rich
Requires-Dist: trio
Dynamic: license-file
